metadata/__init__.py
metadata/data_quality/__init__.py
metadata/data_quality/validations/__init__.py
metadata/data_quality/validations/column/__init__.py
metadata/data_quality/validations/column/base/__init__.py
metadata/data_quality/validations/column/base/columnEntropyToBeBetween2.py
metadata/data_quality/validations/column/pandas/__init__.py
metadata/data_quality/validations/column/pandas/columnEntropyToBeBetween2.py
metadata/data_quality/validations/column/sqlalchemy/__init__.py
metadata/data_quality/validations/column/sqlalchemy/columnEntropyToBeBetween2.py
metadata/data_quality/validations/table/__init__.py
metadata/data_quality/validations/table/base/__init__.py
metadata/data_quality/validations/table/base/columnEntropyToBeBetween3.py
metadata/data_quality/validations/table/pandas/__init__.py
metadata/data_quality/validations/table/pandas/columnEntropyToBeBetween3.py
metadata/data_quality/validations/table/sqlalchemy/__init__.py
metadata/data_quality/validations/table/sqlalchemy/columnEntropyToBeBetween3.py
ue_om_tests-0.0.1.dist-info/LICENSE
ue_om_tests-0.0.1.dist-info/METADATA
ue_om_tests-0.0.1.dist-info/WHEEL
ue_om_tests-0.0.1.dist-info/top_level.txt
ue_om_tests-0.0.1.dist-info/RECORD
