Metadata-Version: 2.1
Name: ue-om-tests
Version: 0.0.1
Summary: Small package to extend metadata functionality
Author-email: UE <bigdata-gcp@rcs.it>
Project-URL: Homepage, https://github.com/pypa/sampleproject
Project-URL: Issues, https://github.com/pypa/sampleproject/issues
Classifier: Programming Language :: Python :: 3
Classifier: License :: OSI Approved :: MIT License
Classifier: Operating System :: OS Independent
Requires-Python: >=3.8
License-File: LICENSE
